[
    "info",
    {
        "image_name": "swing005_149",
        "image_id": 19,
        "person_count": 1
    },
    "key",
    {
        "keypoint_index": [
            [
                [
                    654,
                    121,
                    1
                ],
                [
                    684,
                    170,
                    1
                ],
                [
                    654,
                    217,
                    1
                ],
                [
                    666,
                    302,
                    1
                ],
                [
                    697,
                    212,
                    1
                ],
                [
                    689,
                    148,
                    0
                ],
                [
                    631,
                    123,
                    1
                ],
                [
                    613,
                    225,
                    1
                ],
                [
                    659,
                    192,
                    0
                ],
                [
                    640,
                    133,
                    0
                ],
                [
                    692,
                    388,
                    1
                ],
                [
                    648,
                    525,
                    1
                ],
                [
                    564,
                    617,
                    1
                ],
                [
                    662,
                    386,
                    1
                ],
                [
                    696,
                    515,
                    1
                ],
                [
                    707,
                    650,
                    1
                ],
                [
                    741,
                    668,
                    1
                ],
                [
                    697,
                    666,
                    1
                ],
                [
                    543,
                    672,
                    1
                ],
                [
                    549,
                    613,
                    1
                ],
                [
                    370,
                    233,
                    1
                ]
            ]
        ],
        "image_id": 19
    }
]