[
    "info",
    {
        "image_name": "swing019_48",
        "person_count": 1,
        "image_id": 11
    },
    "key",
    {
        "keypoint_index": [
            [
                [
                    665,
                    163,
                    1
                ],
                [
                    654,
                    219,
                    1
                ],
                [
                    635,
                    227,
                    1
                ],
                [
                    635,
                    287,
                    1
                ],
                [
                    599,
                    212,
                    1
                ],
                [
                    558,
                    263,
                    1
                ],
                [
                    519,
                    279,
                    0
                ],
                [
                    679,
                    246,
                    1
                ],
                [
                    594,
                    273,
                    1
                ],
                [
                    533,
                    281,
                    1
                ],
                [
                    603,
                    347,
                    1
                ],
                [
                    584,
                    431,
                    1
                ],
                [
                    570,
                    523,
                    1
                ],
                [
                    662,
                    351,
                    1
                ],
                [
                    678,
                    437,
                    1
                ],
                [
                    678,
                    529,
                    1
                ],
                [
                    684,
                    555,
                    1
                ],
                [
                    666,
                    539,
                    1
                ],
                [
                    564,
                    552,
                    1
                ],
                [
                    572,
                    531,
                    1
                ],
                [
                    348,
                    111,
                    1
                ]
            ]
        ],
        "image_id": 11
    }
]