{
	"swing014_16.png": [
		"info",
		{
			"person_count": 1,
			"image_name": "swing014_16",
			"image_id": 1
		},
		"key",
		{
			"keypoint_index": [
				[
					[
						623,
						258,
						1
					],
					[
						613,
						312,
						1
					],
					[
						627,
						331,
						1
					],
					[
						626,
						380,
						1
					],
					[
						580,
						337,
						1
					],
					[
						601,
						413,
						1
					],
					[
						633,
						462,
						1
					],
					[
						676,
						323,
						1
					],
					[
						666,
						394,
						1
					],
					[
						652,
						458,
						1
					],
					[
						598,
						431,
						1
					],
					[
						576,
						519,
						1
					],
					[
						568,
						619,
						1
					],
					[
						651,
						429,
						1
					],
					[
						666,
						523,
						1
					],
					[
						678,
						619,
						1
					],
					[
						680,
						641,
						1
					],
					[
						670,
						629,
						1
					],
					[
						566,
						643,
						1
					],
					[
						570,
						629,
						1
					],
					[
						598,
						674,
						1
					]
				]
			],
			"image_id": 1
		}
	],
	"swing014_35.png": [
		"info",
		{
			"person_count": 1,
			"image_name": "swing014_35",
			"image_id": 2
		},
		"key",
		{
			"keypoint_index": [
				[
					[
						619,
						263,
						1
					],
					[
						597,
						311,
						1
					],
					[
						604,
						323,
						1
					],
					[
						608,
						382,
						1
					],
					[
						570,
						313,
						1
					],
					[
						549,
						376,
						1
					],
					[
						532,
						428,
						1
					],
					[
						648,
						345,
						1
					],
					[
						615,
						398,
						1
					],
					[
						545,
						441,
						1
					],
					[
						582,
						435,
						1
					],
					[
						560,
						519,
						1
					],
					[
						566,
						617,
						1
					],
					[
						635,
						443,
						1
					],
					[
						662,
						525,
						1
					],
					[
						678,
						619,
						1
					],
					[
						680,
						643,
						1
					],
					[
						670,
						629,
						1
					],
					[
						564,
						643,
						1
					],
					[
						570,
						625,
						1
					],
					[
						305,
						410,
						1
					]
				]
			],
			"image_id": 2
		}
	],
	"swing014_42.png": [
		"info",
		{
			"person_count": 1,
			"image_name": "swing014_42",
			"image_id": 3
		},
		"key",
		{
			"keypoint_index": [
				[
					[
						617,
						266,
						1
					],
					[
						601,
						310,
						1
					],
					[
						603,
						325,
						1
					],
					[
						605,
						384,
						1
					],
					[
						580,
						306,
						1
					],
					[
						539,
						341,
						1
					],
					[
						490,
						347,
						1
					],
					[
						633,
						356,
						1
					],
					[
						558,
						366,
						1
					],
					[
						492,
						357,
						1
					],
					[
						580,
						439,
						1
					],
					[
						558,
						519,
						1
					],
					[
						566,
						617,
						1
					],
					[
						633,
						445,
						1
					],
					[
						654,
						531,
						1
					],
					[
						676,
						619,
						1
					],
					[
						682,
						645,
						1
					],
					[
						668,
						629,
						1
					],
					[
						564,
						643,
						1
					],
					[
						570,
						625,
						1
					],
					[
						456,
						186,
						1
					]
				]
			],
			"image_id": 3
		}
	],
	"swing014_49.png": [
		"info",
		{
			"person_count": 1,
			"image_name": "swing014_49",
			"image_id": 4
		},
		"key",
		{
			"keypoint_index": [
				[
					[
						613,
						264,
						1
					],
					[
						601,
						311,
						1
					],
					[
						603,
						325,
						1
					],
					[
						606,
						383,
						1
					],
					[
						588,
						306,
						1
					],
					[
						555,
						328,
						1
					],
					[
						506,
						315,
						1
					],
					[
						614,
						360,
						1
					],
					[
						545,
						349,
						1
					],
					[
						490,
						319,
						1
					],
					[
						582,
						435,
						1
					],
					[
						558,
						521,
						1
					],
					[
						564,
						619,
						1
					],
					[
						633,
						445,
						1
					],
					[
						652,
						533,
						1
					],
					[
						676,
						619,
						1
					],
					[
						680,
						645,
						1
					],
					[
						668,
						627,
						1
					],
					[
						562,
						643,
						1
					],
					[
						570,
						625,
						1
					],
					[
						602,
						166,
						1
					]
				]
			],
			"image_id": 4
		}
	],
	"swing014_65.png": [
		"info",
		{
			"person_count": 1,
			"image_name": "swing014_65",
			"image_id": 5
		},
		"key",
		{
			"keypoint_index": [
				[
					[
						611,
						270,
						1
					],
					[
						604,
						318,
						1
					],
					[
						600,
						337,
						1
					],
					[
						603,
						387,
						1
					],
					[
						603,
						305,
						0
					],
					[
						560,
						304,
						1
					],
					[
						531,
						282,
						1
					],
					[
						604,
						362,
						1
					],
					[
						543,
						337,
						1
					],
					[
						509,
						288,
						1
					],
					[
						578,
						441,
						1
					],
					[
						556,
						519,
						1
					],
					[
						560,
						619,
						1
					],
					[
						627,
						449,
						1
					],
					[
						648,
						539,
						1
					],
					[
						674,
						619,
						1
					],
					[
						680,
						643,
						1
					],
					[
						670,
						627,
						1
					],
					[
						562,
						639,
						1
					],
					[
						570,
						627,
						1
					],
					[
						711,
						185,
						1
					]
				]
			],
			"image_id": 5
		}
	],
	"swing014_68.png": [
		"info",
		{
			"person_count": 1,
			"image_name": "swing014_68",
			"image_id": 6
		},
		"key",
		{
			"keypoint_index": [
				[
					[
						609,
						272,
						1
					],
					[
						598,
						321,
						1
					],
					[
						601,
						337,
						1
					],
					[
						604,
						386,
						1
					],
					[
						617,
						291,
						0
					],
					[
						576,
						286,
						1
					],
					[
						547,
						263,
						1
					],
					[
						596,
						362,
						1
					],
					[
						541,
						323,
						1
					],
					[
						525,
						272,
						1
					],
					[
						576,
						443,
						1
					],
					[
						556,
						517,
						1
					],
					[
						560,
						619,
						1
					],
					[
						623,
						447,
						1
					],
					[
						639,
						537,
						1
					],
					[
						672,
						619,
						1
					],
					[
						680,
						643,
						1
					],
					[
						670,
						627,
						1
					],
					[
						562,
						641,
						1
					],
					[
						570,
						627,
						1
					],
					[
						744,
						261,
						1
					]
				]
			],
			"image_id": 6
		}
	],
	"swing014_72.png": [
		"info",
		{
			"person_count": 1,
			"image_name": "swing014_72",
			"image_id": 7
		},
		"key",
		{
			"keypoint_index": [
				[
					[
						607,
						278,
						1
					],
					[
						596,
						327,
						1
					],
					[
						610,
						343,
						1
					],
					[
						599,
						400,
						1
					],
					[
						633,
						293,
						1
					],
					[
						602,
						274,
						0
					],
					[
						566,
						261,
						1
					],
					[
						600,
						364,
						1
					],
					[
						552,
						319,
						1
					],
					[
						539,
						261,
						1
					],
					[
						582,
						439,
						1
					],
					[
						556,
						515,
						1
					],
					[
						560,
						619,
						1
					],
					[
						631,
						449,
						1
					],
					[
						635,
						537,
						1
					],
					[
						670,
						619,
						1
					],
					[
						680,
						645,
						1
					],
					[
						668,
						627,
						1
					],
					[
						560,
						641,
						1
					],
					[
						570,
						629,
						1
					],
					[
						702,
						359,
						1
					]
				]
			],
			"image_id": 7
		}
	],
	"swing014_76.png": [
		"info",
		{
			"person_count": 1,
			"image_name": "swing014_76",
			"image_id": 8
		},
		"key",
		{
			"keypoint_index": [
				[
					[
						605,
						270,
						1
					],
					[
						600,
						321,
						1
					],
					[
						610,
						337,
						1
					],
					[
						612,
						388,
						1
					],
					[
						626,
						299,
						0
					],
					[
						583,
						297,
						1
					],
					[
						543,
						278,
						1
					],
					[
						612,
						358,
						1
					],
					[
						554,
						331,
						1
					],
					[
						527,
						286,
						1
					],
					[
						590,
						443,
						1
					],
					[
						562,
						517,
						1
					],
					[
						562,
						619,
						1
					],
					[
						637,
						447,
						1
					],
					[
						650,
						537,
						1
					],
					[
						670,
						617,
						1
					],
					[
						680,
						643,
						1
					],
					[
						666,
						623,
						1
					],
					[
						560,
						643,
						1
					],
					[
						570,
						631,
						1
					],
					[
						741,
						283,
						1
					]
				]
			],
			"image_id": 8
		}
	],
	"swing014_77.png": [
		"info",
		{
			"person_count": 1,
			"image_name": "swing014_77",
			"image_id": 9
		},
		"key",
		{
			"keypoint_index": [
				[
					[
						605,
						269,
						1
					],
					[
						603,
						311,
						1
					],
					[
						608,
						332,
						1
					],
					[
						615,
						385,
						1
					],
					[
						624,
						302,
						1
					],
					[
						570,
						314,
						1
					],
					[
						534,
						299,
						1
					],
					[
						620,
						359,
						1
					],
					[
						570,
						345,
						1
					],
					[
						523,
						306,
						1
					],
					[
						596,
						443,
						1
					],
					[
						564,
						517,
						1
					],
					[
						562,
						619,
						1
					],
					[
						647,
						445,
						1
					],
					[
						660,
						535,
						1
					],
					[
						672,
						617,
						1
					],
					[
						680,
						643,
						1
					],
					[
						666,
						623,
						1
					],
					[
						560,
						641,
						1
					],
					[
						568,
						631,
						1
					],
					[
						729,
						230,
						1
					]
				]
			],
			"image_id": 9
		}
	],
	"swing014_78.png": [
		"info",
		{
			"person_count": 1,
			"image_name": "swing014_78",
			"image_id": 10
		},
		"key",
		{
			"keypoint_index": [
				[
					[
						606,
						268,
						1
					],
					[
						605,
						315,
						1
					],
					[
						611,
						334,
						1
					],
					[
						618,
						384,
						1
					],
					[
						586,
						304,
						1
					],
					[
						571,
						334,
						1
					],
					[
						525,
						326,
						1
					],
					[
						635,
						352,
						1
					],
					[
						561,
						355,
						1
					],
					[
						517,
						337,
						1
					],
					[
						600,
						443,
						1
					],
					[
						568,
						521,
						1
					],
					[
						562,
						619,
						1
					],
					[
						651,
						445,
						1
					],
					[
						668,
						534,
						1
					],
					[
						675,
						618,
						1
					],
					[
						682,
						648,
						1
					],
					[
						671,
						637,
						1
					],
					[
						560,
						643,
						1
					],
					[
						568,
						631,
						1
					],
					[
						664,
						179,
						1
					]
				]
			],
			"image_id": 10
		}
	],
	"swing014_79.png": [
		"info",
		{
			"person_count": 1,
			"image_name": "swing014_79",
			"image_id": 11
		},
		"key",
		{
			"keypoint_index": [
				[
					[
						610,
						267,
						1
					],
					[
						608,
						318,
						1
					],
					[
						610,
						339,
						1
					],
					[
						621,
						378,
						1
					],
					[
						578,
						310,
						1
					],
					[
						574,
						355,
						1
					],
					[
						523,
						363,
						1
					],
					[
						649,
						351,
						1
					],
					[
						582,
						371,
						1
					],
					[
						523,
						378,
						1
					],
					[
						603,
						435,
						1
					],
					[
						570,
						521,
						1
					],
					[
						562,
						621,
						1
					],
					[
						660,
						441,
						1
					],
					[
						680,
						525,
						1
					],
					[
						680,
						619,
						1
					],
					[
						682,
						645,
						1
					],
					[
						668,
						631,
						1
					],
					[
						560,
						643,
						1
					],
					[
						568,
						633,
						1
					],
					[
						545,
						180,
						1
					]
				]
			],
			"image_id": 11
		}
	],
	"swing014_80.png": [
		"info",
		{
			"person_count": 1,
			"image_name": "swing014_80",
			"image_id": 12
		},
		"key",
		{
			"keypoint_index": [
				[
					[
						609,
						262,
						1
					],
					[
						614,
						313,
						1
					],
					[
						614,
						331,
						1
					],
					[
						623,
						375,
						1
					],
					[
						570,
						319,
						1
					],
					[
						572,
						372,
						1
					],
					[
						539,
						405,
						1
					],
					[
						656,
						333,
						1
					],
					[
						606,
						390,
						1
					],
					[
						549,
						416,
						1
					],
					[
						607,
						431,
						1
					],
					[
						574,
						519,
						1
					],
					[
						564,
						621,
						1
					],
					[
						664,
						431,
						1
					],
					[
						682,
						523,
						1
					],
					[
						680,
						619,
						1
					],
					[
						682,
						645,
						1
					],
					[
						668,
						631,
						1
					],
					[
						562,
						643,
						1
					],
					[
						568,
						633,
						1
					],
					[
						394,
						288,
						1
					]
				]
			],
			"image_id": 12
		}
	],
	"swing014_81.png": [
		"info",
		{
			"person_count": 1,
			"image_name": "swing014_81",
			"image_id": 13
		},
		"key",
		{
			"keypoint_index": [
				[
					[
						606,
						257,
						1
					],
					[
						614,
						311,
						1
					],
					[
						615,
						316,
						1
					],
					[
						627,
						371,
						1
					],
					[
						570,
						321,
						1
					],
					[
						576,
						382,
						1
					],
					[
						574,
						429,
						1
					],
					[
						664,
						311,
						1
					],
					[
						641,
						385,
						1
					],
					[
						593,
						435,
						1
					],
					[
						609,
						427,
						1
					],
					[
						584,
						519,
						1
					],
					[
						564,
						619,
						1
					],
					[
						666,
						427,
						1
					],
					[
						682,
						519,
						1
					],
					[
						680,
						619,
						1
					],
					[
						682,
						645,
						1
					],
					[
						672,
						629,
						1
					],
					[
						562,
						645,
						1
					],
					[
						568,
						631,
						1
					],
					[
						376,
						539,
						1
					]
				]
			],
			"image_id": 13
		}
	],
	"swing014_82.png": [
		"info",
		{
			"person_count": 1,
			"image_name": "swing014_82",
			"image_id": 14
		},
		"key",
		{
			"keypoint_index": [
				[
					[
						603,
						252,
						1
					],
					[
						614,
						303,
						1
					],
					[
						617,
						308,
						1
					],
					[
						628,
						365,
						1
					],
					[
						570,
						323,
						1
					],
					[
						582,
						384,
						1
					],
					[
						613,
						445,
						1
					],
					[
						664,
						294,
						1
					],
					[
						664,
						367,
						1
					],
					[
						636,
						434,
						1
					],
					[
						613,
						427,
						1
					],
					[
						586,
						517,
						1
					],
					[
						562,
						619,
						1
					],
					[
						666,
						419,
						1
					],
					[
						680,
						517,
						1
					],
					[
						680,
						617,
						1
					],
					[
						682,
						643,
						1
					],
					[
						674,
						623,
						1
					],
					[
						564,
						645,
						1
					],
					[
						566,
						629,
						1
					],
					[
						636,
						664,
						1
					]
				]
			],
			"image_id": 14
		}
	]
}