{
	"swing001_16.png": [
		"info",
		{
			"image_id": 1,
			"person_count": 1,
			"image_name": "swing001_16"
		},
		"key",
		{
			"image_id": 1,
			"keypoint_index": [
				[
					[
						595,
						215,
						1
					],
					[
						590,
						278,
						1
					],
					[
						625,
						288,
						1
					],
					[
						647,
						345,
						1
					],
					[
						609,
						276,
						0
					],
					[
						585,
						355,
						1
					],
					[
						548,
						406,
						0
					],
					[
						641,
						298,
						1
					],
					[
						592,
						366,
						1
					],
					[
						551,
						411,
						1
					],
					[
						650,
						406,
						1
					],
					[
						621,
						505,
						1
					],
					[
						609,
						623,
						1
					],
					[
						690,
						402,
						1
					],
					[
						696,
						519,
						1
					],
					[
						729,
						633,
						1
					],
					[
						709,
						658,
						1
					],
					[
						739,
						645,
						1
					],
					[
						570,
						646,
						1
					],
					[
						619,
						637,
						1
					],
					[
						306,
						423,
						1
					]
				]
			]
		}
	],
	"swing001_17.png": [
		"info",
		{
			"image_id": 2,
			"person_count": 1,
			"image_name": "swing001_17"
		},
		"key",
		{
			"image_id": 2,
			"keypoint_index": [
				[
					[
						596,
						217,
						1
					],
					[
						586,
						276,
						1
					],
					[
						625,
						290,
						1
					],
					[
						646,
						349,
						1
					],
					[
						617,
						286,
						0
					],
					[
						576,
						348,
						0
					],
					[
						537,
						381,
						0
					],
					[
						633,
						292,
						1
					],
					[
						576,
						351,
						1
					],
					[
						543,
						382,
						1
					],
					[
						650,
						411,
						1
					],
					[
						621,
						507,
						1
					],
					[
						609,
						623,
						1
					],
					[
						686,
						407,
						1
					],
					[
						694,
						519,
						1
					],
					[
						729,
						631,
						1
					],
					[
						709,
						658,
						1
					],
					[
						739,
						643,
						1
					],
					[
						568,
						646,
						1
					],
					[
						619,
						637,
						1
					],
					[
						365,
						298,
						1
					]
				]
			]
		}
	],
	"swing001_18.png": [
		"info",
		{
			"image_id": 3,
			"person_count": 1,
			"image_name": "swing001_18"
		},
		"key",
		{
			"image_id": 3,
			"keypoint_index": [
				[
					[
						596,
						221,
						1
					],
					[
						586,
						284,
						1
					],
					[
						631,
						292,
						1
					],
					[
						649,
						350,
						1
					],
					[
						635,
						280,
						0
					],
					[
						579,
						341,
						0
					],
					[
						533,
						371,
						0
					],
					[
						625,
						304,
						1
					],
					[
						582,
						345,
						1
					],
					[
						531,
						375,
						1
					],
					[
						650,
						409,
						1
					],
					[
						621,
						507,
						1
					],
					[
						611,
						625,
						1
					],
					[
						686,
						407,
						1
					],
					[
						692,
						521,
						1
					],
					[
						729,
						633,
						1
					],
					[
						709,
						658,
						1
					],
					[
						739,
						643,
						1
					],
					[
						570,
						646,
						1
					],
					[
						619,
						637,
						1
					],
					[
						407,
						234,
						1
					]
				]
			]
		}
	],
	"swing001_1.png": [
		"info",
		{
			"image_id": 4,
			"person_count": 1,
			"image_name": "swing001_1"
		},
		"key",
		{
			"image_id": 4,
			"keypoint_index": [
				[
					[
						594,
						214,
						1
					],
					[
						588,
						272,
						1
					],
					[
						627,
						290,
						1
					],
					[
						650,
						348,
						1
					],
					[
						592,
						302,
						1
					],
					[
						609,
						378,
						1
					],
					[
						619,
						449,
						1
					],
					[
						660,
						280,
						1
					],
					[
						654,
						374,
						1
					],
					[
						639,
						441,
						1
					],
					[
						650,
						408,
						1
					],
					[
						619,
						511,
						1
					],
					[
						611,
						625,
						1
					],
					[
						699,
						404,
						1
					],
					[
						707,
						513,
						1
					],
					[
						731,
						635,
						1
					],
					[
						709,
						660,
						1
					],
					[
						739,
						645,
						1
					],
					[
						570,
						647,
						1
					],
					[
						619,
						637,
						1
					],
					[
						462,
						698,
						1
					]
				]
			]
		}
	],
	"swing001_21.png": [
		"info",
		{
			"image_id": 5,
			"person_count": 1,
			"image_name": "swing001_21"
		},
		"key",
		{
			"image_id": 5,
			"keypoint_index": [
				[
					[
						597,
						220,
						1
					],
					[
						588,
						282,
						1
					],
					[
						633,
						284,
						1
					],
					[
						651,
						348,
						1
					],
					[
						645,
						272,
						1
					],
					[
						591,
						312,
						0
					],
					[
						552,
						306,
						0
					],
					[
						623,
						298,
						1
					],
					[
						576,
						319,
						1
					],
					[
						543,
						306,
						1
					],
					[
						654,
						413,
						1
					],
					[
						621,
						507,
						1
					],
					[
						611,
						625,
						1
					],
					[
						684,
						411,
						1
					],
					[
						684,
						525,
						1
					],
					[
						729,
						633,
						1
					],
					[
						709,
						658,
						1
					],
					[
						739,
						641,
						1
					],
					[
						570,
						646,
						1
					],
					[
						619,
						637,
						1
					],
					[
						581,
						68,
						1
					]
				]
			]
		}
	],
	"swing001_23.png": [
		"info",
		{
			"image_id": 6,
			"person_count": 1,
			"image_name": "swing001_23"
		},
		"key",
		{
			"image_id": 6,
			"keypoint_index": [
				[
					[
						590,
						223,
						1
					],
					[
						578,
						276,
						1
					],
					[
						621,
						288,
						1
					],
					[
						644,
						349,
						1
					],
					[
						647,
						272,
						1
					],
					[
						600,
						282,
						0
					],
					[
						570,
						268,
						0
					],
					[
						602,
						304,
						1
					],
					[
						575,
						297,
						1
					],
					[
						559,
						267,
						0
					],
					[
						650,
						411,
						1
					],
					[
						619,
						507,
						1
					],
					[
						611,
						625,
						1
					],
					[
						680,
						409,
						1
					],
					[
						682,
						527,
						1
					],
					[
						729,
						633,
						1
					],
					[
						709,
						660,
						1
					],
					[
						741,
						643,
						1
					],
					[
						570,
						646,
						1
					],
					[
						619,
						637,
						1
					],
					[
						762,
						24,
						1
					]
				]
			]
		}
	],
	"swing001_29.png": [
		"info",
		{
			"image_id": 7,
			"person_count": 1,
			"image_name": "swing001_29"
		},
		"key",
		{
			"image_id": 7,
			"keypoint_index": [
				[
					[
						592,
						218,
						1
					],
					[
						580,
						274,
						1
					],
					[
						623,
						282,
						1
					],
					[
						644,
						347,
						1
					],
					[
						652,
						270,
						1
					],
					[
						612,
						262,
						0
					],
					[
						613,
						221,
						0
					],
					[
						597,
						298,
						1
					],
					[
						591,
						257,
						0
					],
					[
						605,
						214,
						1
					],
					[
						650,
						411,
						1
					],
					[
						617,
						511,
						1
					],
					[
						611,
						625,
						1
					],
					[
						678,
						411,
						1
					],
					[
						678,
						529,
						1
					],
					[
						727,
						631,
						1
					],
					[
						707,
						660,
						1
					],
					[
						741,
						639,
						1
					],
					[
						570,
						645,
						1
					],
					[
						619,
						637,
						1
					],
					[
						843,
						138,
						1
					]
				]
			]
		}
	],
	"swing001_30.png": [
		"info",
		{
			"image_id": 8,
			"person_count": 1,
			"image_name": "swing001_30"
		},
		"key",
		{
			"image_id": 8,
			"keypoint_index": [
				[
					[
						592,
						216,
						1
					],
					[
						578,
						270,
						1
					],
					[
						621,
						284,
						1
					],
					[
						643,
						348,
						1
					],
					[
						649,
						272,
						1
					],
					[
						614,
						260,
						0
					],
					[
						611,
						223,
						0
					],
					[
						594,
						296,
						1
					],
					[
						592,
						260,
						0
					],
					[
						605,
						212,
						1
					],
					[
						650,
						413,
						1
					],
					[
						617,
						513,
						1
					],
					[
						611,
						625,
						1
					],
					[
						682,
						413,
						1
					],
					[
						678,
						529,
						1
					],
					[
						727,
						631,
						1
					],
					[
						707,
						660,
						1
					],
					[
						741,
						641,
						1
					],
					[
						572,
						646,
						1
					],
					[
						621,
						637,
						1
					],
					[
						850,
						125,
						1
					]
				]
			]
		}
	],
	"swing001_31.png": [
		"info",
		{
			"image_id": 9,
			"person_count": 1,
			"image_name": "swing001_31"
		},
		"key",
		{
			"image_id": 9,
			"keypoint_index": [
				[
					[
						595,
						216,
						1
					],
					[
						582,
						266,
						1
					],
					[
						623,
						282,
						1
					],
					[
						647,
						346,
						1
					],
					[
						645,
						268,
						1
					],
					[
						610,
						262,
						0
					],
					[
						607,
						231,
						0
					],
					[
						605,
						296,
						1
					],
					[
						589,
						261,
						0
					],
					[
						604,
						223,
						0
					],
					[
						650,
						413,
						1
					],
					[
						617,
						515,
						1
					],
					[
						611,
						625,
						1
					],
					[
						690,
						409,
						1
					],
					[
						682,
						527,
						1
					],
					[
						729,
						633,
						1
					],
					[
						707,
						660,
						1
					],
					[
						741,
						643,
						1
					],
					[
						572,
						646,
						1
					],
					[
						621,
						637,
						1
					],
					[
						851,
						105,
						1
					]
				]
			]
		}
	],
	"swing001_32.png": [
		"info",
		{
			"image_id": 10,
			"person_count": 1,
			"image_name": "swing001_32"
		},
		"key",
		{
			"image_id": 10,
			"keypoint_index": [
				[
					[
						599,
						210,
						1
					],
					[
						584,
						264,
						1
					],
					[
						629,
						280,
						1
					],
					[
						649,
						349,
						1
					],
					[
						645,
						268,
						1
					],
					[
						599,
						284,
						0
					],
					[
						580,
						265,
						0
					],
					[
						615,
						294,
						1
					],
					[
						584,
						296,
						1
					],
					[
						572,
						263,
						1
					],
					[
						646,
						419,
						1
					],
					[
						617,
						519,
						1
					],
					[
						613,
						627,
						1
					],
					[
						690,
						415,
						1
					],
					[
						693,
						525,
						1
					],
					[
						729,
						629,
						1
					],
					[
						707,
						662,
						1
					],
					[
						739,
						641,
						1
					],
					[
						570,
						647,
						1
					],
					[
						621,
						637,
						1
					],
					[
						834,
						88,
						1
					]
				]
			]
		}
	],
	"swing001_33.png": [
		"info",
		{
			"image_id": 11,
			"person_count": 1,
			"image_name": "swing001_33"
		},
		"key",
		{
			"image_id": 11,
			"keypoint_index": [
				[
					[
						599,
						213,
						1
					],
					[
						590,
						274,
						1
					],
					[
						635,
						282,
						1
					],
					[
						654,
						346,
						1
					],
					[
						627,
						284,
						0
					],
					[
						611,
						351,
						1
					],
					[
						544,
						358,
						0
					],
					[
						641,
						282,
						1
					],
					[
						585,
						338,
						1
					],
					[
						539,
						359,
						1
					],
					[
						650,
						411,
						1
					],
					[
						621,
						525,
						1
					],
					[
						609,
						623,
						1
					],
					[
						699,
						409,
						1
					],
					[
						713,
						521,
						1
					],
					[
						731,
						637,
						1
					],
					[
						707,
						664,
						1
					],
					[
						739,
						648,
						1
					],
					[
						574,
						649,
						1
					],
					[
						619,
						635,
						1
					],
					[
						638,
						158,
						1
					]
				]
			]
		}
	],
	"swing001_34.png": [
		"info",
		{
			"image_id": 12,
			"person_count": 1,
			"image_name": "swing001_34"
		},
		"key",
		{
			"image_id": 12,
			"keypoint_index": [
				[
					[
						592,
						218,
						1
					],
					[
						584,
						276,
						1
					],
					[
						635,
						286,
						1
					],
					[
						655,
						349,
						1
					],
					[
						619,
						292,
						1
					],
					[
						617,
						362,
						1
					],
					[
						559,
						405,
						0
					],
					[
						649,
						276,
						1
					],
					[
						612,
						350,
						1
					],
					[
						562,
						405,
						1
					],
					[
						650,
						417,
						1
					],
					[
						633,
						527,
						1
					],
					[
						607,
						621,
						1
					],
					[
						703,
						411,
						1
					],
					[
						715,
						521,
						1
					],
					[
						731,
						637,
						1
					],
					[
						707,
						664,
						1
					],
					[
						739,
						648,
						1
					],
					[
						578,
						650,
						1
					],
					[
						617,
						631,
						1
					],
					[
						457,
						312,
						1
					]
				]
			]
		}
	],
	"swing001_36.png": [
		"info",
		{
			"image_id": 13,
			"person_count": 1,
			"image_name": "swing001_36"
		},
		"key",
		{
			"image_id": 13,
			"keypoint_index": [
				[
					[
						585,
						221,
						1
					],
					[
						588,
						278,
						1
					],
					[
						631,
						278,
						1
					],
					[
						655,
						347,
						1
					],
					[
						603,
						292,
						1
					],
					[
						607,
						353,
						1
					],
					[
						603,
						419,
						0
					],
					[
						654,
						268,
						1
					],
					[
						643,
						343,
						1
					],
					[
						605,
						423,
						1
					],
					[
						656,
						417,
						1
					],
					[
						646,
						525,
						1
					],
					[
						607,
						619,
						1
					],
					[
						709,
						411,
						1
					],
					[
						717,
						521,
						1
					],
					[
						731,
						637,
						1
					],
					[
						707,
						662,
						1
					],
					[
						739,
						648,
						1
					],
					[
						580,
						650,
						1
					],
					[
						613,
						629,
						1
					],
					[
						357,
						652,
						1
					]
				]
			]
		}
	],
	"swing001_37.png": [
		"info",
		{
			"image_id": 14,
			"person_count": 1,
			"image_name": "swing001_37"
		},
		"key",
		{
			"image_id": 14,
			"keypoint_index": [
				[
					[
						582,
						225,
						1
					],
					[
						586,
						288,
						1
					],
					[
						623,
						282,
						1
					],
					[
						654,
						344,
						1
					],
					[
						596,
						304,
						1
					],
					[
						611,
						366,
						1
					],
					[
						633,
						427,
						1
					],
					[
						652,
						263,
						1
					],
					[
						660,
						341,
						1
					],
					[
						652,
						413,
						1
					],
					[
						658,
						409,
						1
					],
					[
						648,
						525,
						1
					],
					[
						607,
						619,
						1
					],
					[
						711,
						402,
						1
					],
					[
						723,
						519,
						1
					],
					[
						731,
						637,
						1
					],
					[
						709,
						662,
						1
					],
					[
						737,
						647,
						1
					],
					[
						580,
						650,
						1
					],
					[
						613,
						627,
						1
					],
					[
						532,
						685,
						1
					]
				]
			]
		}
	],
	"swing001_39.png": [
		"info",
		{
			"image_id": 15,
			"person_count": 1,
			"image_name": "swing001_39"
		},
		"key",
		{
			"image_id": 15,
			"keypoint_index": [
				[
					[
						555,
						247,
						1
					],
					[
						593,
						292,
						1
					],
					[
						619,
						294,
						1
					],
					[
						655,
						340,
						1
					],
					[
						617,
						333,
						1
					],
					[
						682,
						324,
						1
					],
					[
						761,
						313,
						1
					],
					[
						637,
						257,
						1
					],
					[
						697,
						290,
						1
					],
					[
						763,
						314,
						0
					],
					[
						666,
						409,
						1
					],
					[
						648,
						515,
						1
					],
					[
						605,
						617,
						1
					],
					[
						721,
						402,
						1
					],
					[
						725,
						517,
						1
					],
					[
						731,
						635,
						1
					],
					[
						709,
						662,
						1
					],
					[
						735,
						647,
						1
					],
					[
						582,
						650,
						1
					],
					[
						609,
						625,
						1
					],
					[
						1067,
						187,
						1
					]
				]
			]
		}
	],
	"swing001_41.png": [
		"info",
		{
			"image_id": 16,
			"person_count": 1,
			"image_name": "swing001_41"
		},
		"key",
		{
			"image_id": 16,
			"keypoint_index": [
				[
					[
						564,
						249,
						1
					],
					[
						609,
						283,
						1
					],
					[
						630,
						281,
						1
					],
					[
						665,
						342,
						1
					],
					[
						622,
						320,
						1
					],
					[
						703,
						274,
						1
					],
					[
						770,
						226,
						1
					],
					[
						635,
						263,
						1
					],
					[
						705,
						263,
						0
					],
					[
						759,
						249,
						1
					],
					[
						678,
						409,
						1
					],
					[
						656,
						521,
						1
					],
					[
						605,
						615,
						1
					],
					[
						735,
						400,
						1
					],
					[
						727,
						517,
						1
					],
					[
						729,
						639,
						1
					],
					[
						709,
						662,
						1
					],
					[
						733,
						649,
						1
					],
					[
						580,
						649,
						1
					],
					[
						609,
						623,
						1
					],
					[
						844,
						43,
						1
					]
				]
			]
		}
	],
	"swing001_42.png": [
		"info",
		{
			"image_id": 17,
			"person_count": 1,
			"image_name": "swing001_42"
		},
		"key",
		{
			"image_id": 17,
			"keypoint_index": [
				[
					[
						572,
						241,
						1
					],
					[
						620,
						277,
						1
					],
					[
						643,
						290,
						1
					],
					[
						673,
						349,
						1
					],
					[
						635,
						317,
						1
					],
					[
						709,
						254,
						1
					],
					[
						756,
						224,
						1
					],
					[
						636,
						262,
						1
					],
					[
						702,
						258,
						0
					],
					[
						752,
						206,
						1
					],
					[
						678,
						411,
						1
					],
					[
						662,
						519,
						1
					],
					[
						603,
						613,
						1
					],
					[
						733,
						407,
						1
					],
					[
						729,
						521,
						1
					],
					[
						729,
						637,
						1
					],
					[
						709,
						662,
						1
					],
					[
						733,
						649,
						1
					],
					[
						582,
						646,
						1
					],
					[
						605,
						623,
						1
					],
					[
						680,
						78,
						1
					]
				]
			]
		}
	],
	"swing001_43.png": [
		"info",
		{
			"image_id": 18,
			"person_count": 1,
			"image_name": "swing001_43"
		},
		"key",
		{
			"image_id": 18,
			"keypoint_index": [
				[
					[
						592,
						227,
						1
					],
					[
						636,
						258,
						1
					],
					[
						647,
						282,
						1
					],
					[
						677,
						343,
						1
					],
					[
						650,
						306,
						1
					],
					[
						698,
						229,
						1
					],
					[
						714,
						183,
						1
					],
					[
						650,
						259,
						1
					],
					[
						708,
						252,
						1
					],
					[
						733,
						191,
						1
					],
					[
						682,
						409,
						1
					],
					[
						672,
						519,
						1
					],
					[
						598,
						603,
						1
					],
					[
						735,
						402,
						1
					],
					[
						729,
						521,
						1
					],
					[
						729,
						639,
						1
					],
					[
						709,
						664,
						1
					],
					[
						733,
						650,
						1
					],
					[
						584,
						647,
						1
					],
					[
						586,
						603,
						1
					],
					[
						453,
						231,
						1
					]
				]
			]
		}
	],
	"swing001_47.png": [
		"info",
		{
			"image_id": 19,
			"person_count": 1,
			"image_name": "swing001_47"
		},
		"key",
		{
			"image_id": 19,
			"keypoint_index": [
				[
					[
						621,
						210,
						1
					],
					[
						663,
						246,
						1
					],
					[
						664,
						270,
						0
					],
					[
						701,
						330,
						1
					],
					[
						682,
						289,
						1
					],
					[
						682,
						217,
						1
					],
					[
						654,
						188,
						1
					],
					[
						639,
						261,
						0
					],
					[
						656,
						232,
						0
					],
					[
						650,
						198,
						0
					],
					[
						690,
						423,
						1
					],
					[
						665,
						531,
						1
					],
					[
						591,
						606,
						1
					],
					[
						736,
						409,
						1
					],
					[
						727,
						529,
						1
					],
					[
						728,
						647,
						1
					],
					[
						735,
						661,
						1
					],
					[
						710,
						671,
						1
					],
					[
						575,
						648,
						1
					],
					[
						579,
						593,
						1
					],
					[
						492,
						376,
						1
					]
				]
			]
		}
	],
	"swing001_55.png": [
		"info",
		{
			"image_id": 20,
			"person_count": 1,
			"image_name": "swing001_55"
		},
		"key",
		{
			"image_id": 20,
			"keypoint_index": [
				[
					[
						651,
						201,
						1
					],
					[
						698,
						235,
						1
					],
					[
						678,
						272,
						1
					],
					[
						696,
						339,
						1
					],
					[
						714,
						275,
						1
					],
					[
						681,
						221,
						0
					],
					[
						609,
						214,
						1
					],
					[
						648,
						264,
						0
					],
					[
						620,
						284,
						1
					],
					[
						609,
						225,
						1
					],
					[
						701,
						408,
						1
					],
					[
						664,
						523,
						1
					],
					[
						588,
						609,
						1
					],
					[
						731,
						409,
						1
					],
					[
						723,
						529,
						1
					],
					[
						723,
						643,
						1
					],
					[
						705,
						666,
						1
					],
					[
						725,
						652,
						1
					],
					[
						574,
						650,
						1
					],
					[
						578,
						605,
						1
					],
					[
						784,
						299,
						1
					]
				]
			]
		}
	]
}