[
    "info",
    {
        "image_name": "swing016_68",
        "person_count": 1,
        "image_id": 7
    },
    "key",
    {
        "keypoint_index": [
            [
                [
                    586,
                    240,
                    1
                ],
                [
                    588,
                    276,
                    1
                ],
                [
                    560,
                    276,
                    1
                ],
                [
                    547,
                    320,
                    1
                ],
                [
                    541,
                    259,
                    1
                ],
                [
                    528,
                    261,
                    1
                ],
                [
                    517,
                    245,
                    1
                ],
                [
                    579,
                    303,
                    1
                ],
                [
                    523,
                    288,
                    1
                ],
                [
                    504,
                    249,
                    1
                ],
                [
                    509,
                    359,
                    1
                ],
                [
                    511,
                    431,
                    1
                ],
                [
                    515,
                    507,
                    1
                ],
                [
                    554,
                    366,
                    1
                ],
                [
                    584,
                    433,
                    1
                ],
                [
                    574,
                    496,
                    1
                ],
                [
                    602,
                    511,
                    1
                ],
                [
                    570,
                    507,
                    1
                ],
                [
                    535,
                    523,
                    1
                ],
                [
                    511,
                    515,
                    1
                ],
                [
                    707,
                    204,
                    1
                ]
            ]
        ],
        "image_id": 7
    }
]